asterixparse/__init__.py
asterixparse/asterixparse.py
asterixparse/classesASTERIX/__init__.py
asterixparse/classesASTERIX/classcategory21.py
asterixparse/classesASTERIX/classcategory48.py
asterixparse/classesASTERIX/classmodes.py
asterixparse/classesASTERIX/meteotool.py
asterixparse-0.1.0.dist-info/LICENSE
asterixparse-0.1.0.dist-info/METADATA
asterixparse-0.1.0.dist-info/WHEEL
asterixparse-0.1.0.dist-info/top_level.txt
asterixparse-0.1.0.dist-info/RECORD
