Metadata-Version: 2.1
Name: asterixparse
Version: 0.1.0
Summary: Python project to Decode EUROCONTROL ASTERIX data format messages
Author: Rodrigo Perela
Author-email: rosu.perela@gmail.com
License: MIT License
Project-URL: Bug Reports, https://github.com/rosu123/AsterixParse/issues
Project-URL: Source, https://github.com/rosu123/AsterixParse
Keywords: AsterixParse,ASTERIX,EUROCONTROL,development,ModeS,BDS,Category21,Category48,ADS-B
Classifier: Development Status :: 3 - Alpha
Classifier: Intended Audience :: Developers
Classifier: Topic :: Software Development :: Build Tools
Classifier: License :: OSI Approved :: MIT License
Classifier: Programming Language :: Python :: 3
Classifier: Programming Language :: Python :: 3.6
Classifier: Programming Language :: Python :: 3.7
Classifier: Programming Language :: Python :: 3.8
Classifier: Programming Language :: Python :: 3.9
Classifier: Programming Language :: Python :: 3.10
Classifier: Programming Language :: Python :: 3.11
Classifier: Programming Language :: Python :: 3 :: Only
Requires-Python: >=3.6, <4
License-File: LICENSE
Requires-Dist: pandas >=2.1.4
Requires-Dist: jsonpickle >=2.2.0
Requires-Dist: pymongo >=3.12.0
Requires-Dist: tqdm >=4.65.0
Requires-Dist: fastmeteo >=0.1.1
